{
    "release_id": "l8740-purple-passion-2008",
    "toy_number": "L8740",
    "casting_id": "purple-passion",
    "year": 2008,
    "series_id": "22nd-annual-hot-wheels-collectors-convention",
    "series_index": 4,
    "specs": {
        "color": "Chrome Red",
        "tampo": "Spectraflame Orange & Yellow flames on sides & hood, Spectraflame Orange on top & trunk, convention logo on trunk",
        "base_color": "",
        "base_type": "Plastic",
        "window_color": "Clear",
        "interior_color": "White",
        "wheel_type": {
            "0": "WWRR"
        }
    },
    "country": "Thailand",
    "notes": "3000 Produced",
    "images": {
        "0": "https://static.wikia.nocookie.net/hotwheels/images/5/5f/22nd_Collectors_Convention_Purple_Passion.jpg/revision/latest/scale-to-width-down/75?cb=20200522110451"
    }
}