{
    "release_id": "htv49-mclaren-senna-2024",
    "toy_number": "HTV49",
    "casting_id": "mclaren-senna",
    "year": 2024,
    "series_id": "hw-motor-show-5-pack",
    "series_index": null,
    "specs": {
        "color": "Abyss Black",
        "tampo": "Detailed taillights, McLaren badge on front & rear, Senna wordmark on rear",
        "base_color": "",
        "base_type": "Plastic",
        "window_color": "Smoke tint",
        "interior_color": "Black",
        "wheel_type": {
            "0": "Yellow rim",
            "1": "black PR5"
        }
    },
    "country": "Indonesia",
    "notes": "Base code(s): T05, T35",
    "images": {
        "0": "https://static.wikia.nocookie.net/hotwheels/images/b/bf/2024HWMotorShowSenna-4.jpg/revision/latest/scale-to-width-down/75?cb=20240525032019"
    }
}