{
    "release_id": "54429-fire-eater-2002",
    "toy_number": "54429",
    "casting_id": "fire-eater",
    "year": 2002,
    "series_id": "heat-fleet-5-pack",
    "series_index": null,
    "specs": {
        "color": "Silver",
        "tampo": "Red, White, Black & Yellow tampos",
        "base_color": "",
        "base_type": "Plastic",
        "window_color": "Yellow tint",
        "interior_color": "Yellow tint",
        "wheel_type": {
            "0": "5SP"
        }
    },
    "country": "Thailand",
    "notes": "",
    "images": {
        "0": "https://static.wikia.nocookie.net/hotwheels/images/5/5f/Fire_Eater_silver_heat_fleet_5-pack_2002.JPG/revision/latest/scale-to-width-down/75?cb=20130826211847"
    }
}