{
    "release_id": "gry74-airuption-2021",
    "toy_number": "GRY74",
    "casting_id": "airuption",
    "year": 2021,
    "series_id": "hw-space",
    "series_index": 2,
    "specs": {
        "color": "Metallic Mint Green",
        "tampo": "Blue & teal stripes on top",
        "base_color": "",
        "base_type": "Plastic",
        "window_color": "Black",
        "interior_color": "Black",
        "wheel_type": {
            "0": "Gray tires",
            "1": "Teal Chrome TRAP5"
        }
    },
    "country": "Malaysia",
    "notes": "",
    "images": {
        "0": "https://static.wikia.nocookie.net/hotwheels/images/8/84/Mint_Green_Airuption.jpg/revision/latest/scale-to-width-down/75?cb=20210425041244"
    }
}