{
    "release_id": "n-a-21-ford-bronco-2021",
    "toy_number": "N/A",
    "casting_id": "21-ford-bronco",
    "year": 2021,
    "series_id": "luis-fonsi-special-edition",
    "series_index": null,
    "specs": {
        "color": "White",
        "tampo": "Detailed headlights, \"BRONCO\" on front, Bronco logo on sides, red and black pinstriping, black roof",
        "base_color": "",
        "base_type": "Plastic",
        "window_color": "Tinted (Black)",
        "interior_color": "Black",
        "wheel_type": {
            "0": "RRSW"
        }
    },
    "country": "Malaysia",
    "notes": "21 produced Base code(s):",
    "images": {
        "0": "https://static.wikia.nocookie.net/hotwheels/images/0/0f/21_ford_bronco_Luis_Fonsi.jpg/revision/latest/scale-to-width-down/75?cb=20221004170918"
    }
}