{
    "release_id": "1968-custom-corvette-spectraflame-purple-6215-v6",
    "toy_number": "6215",
    "casting_id": "custom-corvette",
    "year": 1968,
    "series_id": "sweet",
    "series_index": null,
    "specs": {
        "color": "Spectraflame Purple",
        "tampo": "",
        "base_color": "Unpainted",
        "base_type": "Metal",
        "window_color": "Blue tint",
        "interior_color": "Brown",
        "wheel_type": {
            "0": "RL"
        },
        "sticker": ""
    },
    "country": "Hong Kong",
    "notes": "",
    "images": {
        "0": "https://static.wikia.nocookie.net/hotwheels/images/7/71/Dscn2747.jpg/revision/latest?cb=20230929001813"
    }
}