{
    "release_id": "2003-highway-35-world-race-unknown-b0886",
    "toy_number": "B0886",
    "casting_id": "highway-35-world-race",
    "year": 2003,
    "series_id": "unknown",
    "series_index": null,
    "specs": {
        "color": "unknown",
        "tampo": "",
        "base_color": "",
        "base_type": "",
        "window_color": "",
        "interior_color": "",
        "wheel_type": {
            "0": ""
        },
        "series": "15/35",
        "name": "Ballistik"
    },
    "country": "Thailand",
    "notes": "",
    "images": {
        "0": "https://static.wikia.nocookie.net/hotwheels/images/d/db/BanjoBallistik.jpg/revision/latest?cb=20250114124048"
    }
}