{
    "release_id": "hyy57-slide-kick-2025",
    "toy_number": "HYY57",
    "casting_id": "slide-kick",
    "year": 2025,
    "series_id": "experimotors",
    "series_index": 1,
    "specs": {
        "color": "Yellow",
        "tampo": "Dark red, light blue, white, and lime green stripe on sides and top, \"SLIDE KICK\" and HW logo on top, \"SK\" flame logo on sides",
        "base_color": "",
        "base_type": "Plastic",
        "window_color": "",
        "interior_color": "White",
        "wheel_type": {
            "0": "Yellow",
            "1": "White rim 5SP"
        }
    },
    "country": "Malaysia",
    "notes": "Hot Wheels Let's Race Base code(s): T48",
    "images": {
        "0": "https://static.wikia.nocookie.net/hotwheels/images/f/fc/ExperiSlide.jpg/revision/latest/scale-to-width-down/75?cb=20250111110836"
    }
}