{
    "release_id": "jby51-69-ford-mustang-boss-302-2025",
    "toy_number": "JBY51",
    "casting_id": "69-ford-mustang-boss-302",
    "year": 2025,
    "series_id": "mustang-60-years",
    "series_index": 2,
    "specs": {
        "color": "Calypso Corral",
        "tampo": "Detailed headlights and taillights, Boss 302 iconography and trim detailing",
        "base_color": "",
        "base_type": "Plastic",
        "window_color": "Smoke tint",
        "interior_color": "Black",
        "wheel_type": {
            "0": "S5"
        }
    },
    "country": "Thailand",
    "notes": "Base code(s): T37, T38, T39, T41, T43, T48, T48A",
    "images": {
        "0": "https://static.wikia.nocookie.net/hotwheels/images/2/29/JBY51.jpg/revision/latest/scale-to-width-down/75?cb=20250304141758"
    }
}