{
    "release_id": "x6999-the-nash-2025",
    "toy_number": "X6999",
    "casting_id": "the-nash",
    "year": 2025,
    "series_id": "multipack-exclusive",
    "series_index": null,
    "specs": {
        "color": "Metalflake Green",
        "tampo": "White Hot Wheels logo on trunk, white stripes on sides, white/black \"The Nash\" on hood & sides, white roof",
        "base_color": "",
        "base_type": "Plastic",
        "window_color": "Clear",
        "interior_color": "Chrome",
        "wheel_type": {
            "0": "White SK5SP"
        }
    },
    "country": "Malaysia",
    "notes": "",
    "images": {
        "0": "https://static.wikia.nocookie.net/hotwheels/images/3/3d/2025_The_Nash.jpg/revision/latest/scale-to-width-down/75?cb=20250110005302"
    }
}