{
    "release_id": "r0969-subaru-impreza-2010",
    "toy_number": "R0969",
    "casting_id": "subaru-impreza",
    "year": 2010,
    "series_id": "dirt-track-race-5-pack",
    "series_index": null,
    "specs": {
        "color": "Blue",
        "tampo": "Yellow, white & black tampos, Subaru logo",
        "base_color": "",
        "base_type": "Plastic",
        "window_color": "Clear",
        "interior_color": "Gray",
        "wheel_type": {
            "0": "10SP"
        }
    },
    "country": "Thailand",
    "notes": "Base Code(s): C48",
    "images": {
        "0": "https://static.wikia.nocookie.net/hotwheels/images/e/e3/DTR5pkSubaru.jpg/revision/latest/scale-to-width-down/75?cb=20110404104834"
    }
}