[
    {
        "metadata": {
            "name": "Hoto Roto",
            "Debut series": "Rod Squad",
            "image": "HotoRoto.jpg",
            "image_url": "https://static.wikia.nocookie.net/hotwheels/images/8/87/HotoRoto.jpg/revision/latest/scale-to-width-down/268?cb=20250120090700"
        },
        "description": {
            "en-us": "Hoto Roto Debut series Rod Squad Produced 2025 – Present Designer Bryan Zhao Number HYW33",
            "pt-br": ""
        },
        "releases": [
            {
                "Col #": "158/250",
                "Year": "2025",
                "Series": "Rod Squad 10/10",
                "Color": "Matte \"moody\" blue",
                "Tampo": "Gold striping down length of body, \"ホットホィール\" on trunk, \"67\" on roof, Hot Wheels logo, \" ZHAO \", \" ATN \", \"C.\", \" FC \" on air intake",
                "base_color": "Gray",
                "base_type": "Plastic",
                "Window Color": "Smoke tint",
                "Interior Color": "Chrome",
                "Wheel Type": "Grey DD8 & 5SP",
                "Toy #": "HYW33",
                "Country": "Malaysia",
                "Notes": "Hot Wheels Let's Race New Model Base code(s): T50, T50N, U02N",
                "Photo": "https://static.wikia.nocookie.net/hotwheels/images/8/87/HotoRoto.jpg/revision/latest/scale-to-width-down/75?cb=20250120090700"
            },
            {
                "Col #": "158/250",
                "Year": "2025",
                "Series": "Rod Squad 10/10",
                "Color": "White",
                "Tampo": "Gold striping down length of body, \"ホットホィール\" on trunk, \"67\" on roof, Hot Wheels logo, \" ZHAO \", \" ATN \", \"C.\", \" FC \" on air intake",
                "base_color": "Black",
                "base_type": "Plastic",
                "Window Color": "Smoke tint",
                "Interior Color": "Chrome",
                "Wheel Type": "DD8 & 5SP",
                "Toy #": "JBB74",
                "Country": "Malaysia",
                "Notes": "New Model Base code(s): U22N",
                "Photo": "https://static.wikia.nocookie.net/hotwheels/images/f/f8/CosmoHotRod.jpg/revision/latest/scale-to-width-down/75?cb=20250715130206"
            },
            {
                "Col #": "079/250",
                "Year": "2026",
                "Series": "Compact Kings 2/10",
                "Color": "",
                "Tampo": "",
                "base_color": "",
                "base_type": "",
                "Window Color": "",
                "Interior Color": "",
                "Wheel Type": "",
                "Toy #": "JJJ44",
                "Country": "Malaysia",
                "Notes": "Base code(s):",
                "Photo": "https://static.wikia.nocookie.net/hotwheels/images/5/57/BlackRoto.jpg/revision/latest/scale-to-width-down/75?cb=20251216110108"
            }
        ]
    }
]