{
    "release_id": "hcy33-honda-s2000-2022",
    "toy_number": "HCY33",
    "casting_id": "honda-s2000",
    "year": 2022,
    "series_id": "hw-j-imports",
    "series_index": 3,
    "specs": {
        "color": "ZAMAC",
        "tampo": "Detailed headlights & taillights, \"Hot Wheels Ryu\", \"S2000\" badging on sides",
        "base_color": "",
        "base_type": "Plastic",
        "window_color": "Smoke tint",
        "interior_color": "Black",
        "wheel_type": {
            "0": "PR5"
        }
    },
    "country": "Malaysia",
    "notes": "Walmart Exclusive Base code(s): R16, R46",
    "images": {
        "0": "https://static.wikia.nocookie.net/hotwheels/images/7/78/ZAMACS2000.jpg/revision/latest/scale-to-width-down/75?cb=20221105071926"
    }
}