{
    "release_id": "hcy65-automobili-pininfarina-battista-2022",
    "toy_number": "HCY65",
    "casting_id": "automobili-pininfarina-battista",
    "year": 2022,
    "series_id": "red-edition",
    "series_index": 8,
    "specs": {
        "color": "Rosso Nino",
        "tampo": "Detailed headlights, taillights and daytime running lights, \"Battista\" license plate",
        "base_color": "",
        "base_type": "Plastic",
        "window_color": "Heavy smoke tint",
        "interior_color": "Black",
        "wheel_type": {
            "0": "RA6"
        }
    },
    "country": "Malaysia",
    "notes": "Target Exclusive New in Mainline Base code(s): R12",
    "images": {
        "0": "https://static.wikia.nocookie.net/hotwheels/images/7/7a/RossoBattista.jpg/revision/latest/scale-to-width-down/75?cb=20221105072042"
    }
}