{
    "release_id": "x6999-mclaren-p1-2022",
    "toy_number": "X6999",
    "casting_id": "mclaren-p1",
    "year": 2022,
    "series_id": "multipack-exclusive",
    "series_index": null,
    "specs": {
        "color": "Burgundy",
        "tampo": "Detailed headlights & taillights",
        "base_color": "",
        "base_type": "Plastic",
        "window_color": "Smoke tint",
        "interior_color": "Black",
        "wheel_type": {
            "0": "Gray PR5"
        }
    },
    "country": "Malaysia",
    "notes": "Base code(s):",
    "images": {
        "0": "https://static.wikia.nocookie.net/hotwheels/images/a/aa/20221120_155453.jpg/revision/latest/scale-to-width-down/75?cb=20221122193845"
    }
}