{
    "release_id": "x9857-impavido-1-2013",
    "toy_number": "X9857",
    "casting_id": "impavido-1",
    "year": 2013,
    "series_id": "road-rockets-5-pack",
    "series_index": null,
    "specs": {
        "color": "Silver",
        "tampo": "Yellow & Orange Tampos with Hot Wheels logo & White #22 on Side Windows",
        "base_color": "",
        "base_type": "Plastic",
        "window_color": "Aqua blue tint",
        "interior_color": "Chrome",
        "wheel_type": {
            "0": "Aqua Blue & Chrome OH5"
        }
    },
    "country": "Thailand",
    "notes": "Base code(s): F21, F41",
    "images": {
        "0": "https://static.wikia.nocookie.net/hotwheels/images/c/c2/Impavido1Silver.jpg/revision/latest/scale-to-width-down/75?cb=20141201033549"
    }
}