{
    "release_id": "k6135-nitro-doorslammer-2007",
    "toy_number": "K6135",
    "casting_id": "nitro-doorslammer",
    "year": 2007,
    "series_id": "2007-new-models",
    "series_index": 3,
    "specs": {
        "color": "Metalflake Burgundy",
        "tampo": "White, Gold, Black & Red tampos, 'Nitro Door Slammer'",
        "base_color": "",
        "base_type": "Plastic",
        "window_color": "Clear",
        "interior_color": "Chrome",
        "wheel_type": {
            "0": "Gold OH5"
        }
    },
    "country": "Malaysia",
    "notes": "",
    "images": {
        "0": "https://static.wikia.nocookie.net/hotwheels/images/b/bc/FE_Nitro_Doorslammer.jpg/revision/latest/scale-to-width-down/75?cb=20080328040924"
    }
}