{
    "release_id": "m7626-rd-05-2007",
    "toy_number": "M7626",
    "casting_id": "rd-05",
    "year": 2007,
    "series_id": "holiday-hot-rods-3-pack",
    "series_index": null,
    "specs": {
        "color": "Satin Gold",
        "tampo": "No Tampos",
        "base_color": "",
        "base_type": "Plastic",
        "window_color": "Green",
        "interior_color": "Chrome",
        "wheel_type": {
            "0": "OH5"
        }
    },
    "country": "Thailand",
    "notes": "Target Exclusive",
    "images": {
        "0": "https://static.wikia.nocookie.net/hotwheels/images/f/f4/20250425000813.jpg/revision/latest/scale-to-width-down/75?cb=20250425050942"
    }
}