{
    "release_id": "4970-combat-medic-1991",
    "toy_number": "4970",
    "casting_id": "combat-medic",
    "year": 1991,
    "series_id": "mainline",
    "series_index": null,
    "specs": {
        "color": "White",
        "tampo": "Red and Blue \"Air France Cargo\"",
        "base_color": "",
        "base_type": "Plastic",
        "window_color": "Blue tint",
        "interior_color": "Black",
        "wheel_type": {
            "0": "BW"
        }
    },
    "country": "Malaysia",
    "notes": "Named Delivery Truck International only",
    "images": {
        "0": "https://static.wikia.nocookie.net/hotwheels/images/2/2d/1991_del_truck_air_cargo_international.jpg/revision/latest/scale-to-width-down/75?cb=20130210223814"
    }
}