{
    "release_id": "p2407-dodge-ram-1500-2009",
    "toy_number": "P2407",
    "casting_id": "dodge-ram-1500",
    "year": 2009,
    "series_id": "hw-special-features",
    "series_index": 1,
    "specs": {
        "color": "Metalflake Pearl Green",
        "tampo": "Black & Silver graphics on sides, with Silver \"Dodge\" & \"Ram 1500\"",
        "base_color": "",
        "base_type": "Plastic",
        "window_color": "Tinted",
        "interior_color": "Chrome",
        "wheel_type": {
            "0": "Chrome OR5SP"
        }
    },
    "country": "Malaysia",
    "notes": "Also released on Target exclusive snowflake card Base code(s):",
    "images": {
        "0": "https://static.wikia.nocookie.net/hotwheels/images/3/35/Dodge_Ram_1500_2009.jpg/revision/latest/scale-to-width-down/75?cb=20090201011914"
    }
}