{
    "release_id": "bdt98-custom-77-dodge-van-2014",
    "toy_number": "BDT98",
    "casting_id": "custom-77-dodge-van",
    "year": 2014,
    "series_id": "hot-wheels-entertainment-anchorman",
    "series_index": null,
    "specs": {
        "color": "White",
        "tampo": "Red, Blue & Yellow \"KVWN 4 San Diego\"",
        "base_color": "",
        "base_type": "Plastic",
        "window_color": "Clear",
        "interior_color": "Gray",
        "wheel_type": {
            "0": "CDDRR"
        }
    },
    "country": "Malaysia",
    "notes": "Casting modified to inc. satellite dish & rails on top. Base code(s): G32",
    "images": {
        "0": "https://static.wikia.nocookie.net/hotwheels/images/4/40/Dio1-Anchorman_Van-WEB.JPG/revision/latest/scale-to-width-down/75?cb=20150730184154"
    }
}