{
    "release_id": "cdt74-baja-bone-shaker-2015",
    "toy_number": "CDT74",
    "casting_id": "baja-bone-shaker",
    "year": 2015,
    "series_id": "desert-force-5-pack",
    "series_index": null,
    "specs": {
        "color": "Metalflake Dark Gold",
        "tampo": "White & black stripes, star & “5” on sides",
        "base_color": "",
        "base_type": "Plastic",
        "window_color": "",
        "interior_color": "Black",
        "wheel_type": {
            "0": "Tan wheel",
            "1": "chrome gold OR6SP"
        }
    },
    "country": "Malaysia",
    "notes": "",
    "images": {
        "0": "https://static.wikia.nocookie.net/hotwheels/images/a/a1/BajaBoneShakerCDT24.jpg/revision/latest/scale-to-width-down/75?cb=20171007174742"
    }
}