{
    "casting_id": "mr11",
    "name": "MR11",
    "description": {
        "en-us": "MR11 Debut series Germany Exclusive Produced 2014 - Present Designer Marco Reus and Ryu Asada Number BDD12",
        "pt-br": ""
    },
    "releases": [
        "data/releases/2013/cbr63-mr11.json",
        "data/releases/2014/bff63-mr11.json",
        "data/releases/2015/cfk24-mr11.json",
        "data/releases/2015/cfj49-mr11.json",
        "data/releases/2016/dtn35-mr11.json",
        "data/releases/2016/dht24-mr11.json",
        "data/releases/2016/drb32-mr11.json",
        "data/releases/2018/fjw26-mr11.json",
        "data/releases/2018/fkb95-mr11.json",
        "data/releases/2018/fll01-mr11.json",
        "data/releases/2019/fyl23-mr11.json",
        "data/releases/2019/x6999-mr11.json",
        "data/releases/2021/gtn37-mr11.json",
        "data/releases/2021/grp66-mr11.json",
        "data/releases/2022/x6999-mr11.json",
        "data/releases/2023/x6999-mr11.json",
        "data/releases/2024/x6999-mr11.json",
        "data/releases/2025/x6999-mr11.json"
    ],
    "specs": {},
    "designer": "Unknown",
    "debut_year": 2013,
    "manufacturer": "Mattel"
}