{
    "casting_id": "subaru-brz",
    "name": "Subaru BRZ",
    "description": {
        "en-us": "Subaru BRZ Debut series Hot Wheels id: HW Speed Graphics Produced 2021 – Present Designer Mark Jones and Phil Riehlman Number GMK76",
        "pt-br": ""
    },
    "releases": [
        "data/releases/2021/hbg01-subaru-brz.json",
        "data/releases/2025/hyw99-subaru-brz.json",
        "data/releases/2025/hyy12-subaru-brz.json",
        "data/releases/2025/jbb55-subaru-brz.json"
    ],
    "specs": {},
    "designer": "Unknown",
    "debut_year": 2021,
    "manufacturer": "Subaru"
}