{
    "release_id": "0-car-culture-2-packs-abyss-black-hff97",
    "toy_number": "HFF97",
    "casting_id": "car-culture-2-packs",
    "year": 0,
    "series_id": "unknown",
    "series_index": null,
    "specs": {
        "color": "Abyss Black",
        "tampo": "",
        "base_color": "",
        "base_type": "",
        "window_color": "",
        "interior_color": "",
        "wheel_type": {
            "0": "RR5SPM"
        },
        "theme": "McLaren",
        "casting": "McLaren Senna",
        "photo_loose": "",
        "photo_carded": ""
    },
    "country": "",
    "notes": "Base code(s): R40, R42",
    "images": {
        "0": "https://static.wikia.nocookie.net/hotwheels/images/7/75/Car_culture_2-packs_Senna.jpg/revision/latest?cb=20250722213017"
    }
}