{
    "release_id": "0-car-culture-2-packs-yellow-hrr82",
    "toy_number": "HRR82",
    "casting_id": "car-culture-2-packs",
    "year": 0,
    "series_id": "unknown",
    "series_index": null,
    "specs": {
        "color": "Yellow",
        "tampo": "",
        "base_color": "",
        "base_type": "",
        "window_color": "",
        "interior_color": "",
        "wheel_type": {
            "0": "RR8SP"
        },
        "theme": "Porsche",
        "casting": "Porsche 993 GT2",
        "photo_loose": "",
        "photo_carded": ""
    },
    "country": "",
    "notes": "Similar to X8240 Base code(s): T31",
    "images": {
        "0": "https://static.wikia.nocookie.net/hotwheels/images/6/62/25_HW_Porsche_993_GT2_Front.jpg/revision/latest?cb=20250304172136"
    }
}