{
    "release_id": "0-dragstrip-demons-unknown-n8964",
    "toy_number": "N8964",
    "casting_id": "dragstrip-demons",
    "year": 0,
    "series_id": "unknown",
    "series_index": null,
    "specs": {
        "color": "unknown",
        "tampo": "",
        "base_color": "",
        "base_type": "",
        "window_color": "",
        "interior_color": "",
        "wheel_type": {
            "0": ""
        },
        "series": "05/30",
        "model_name": "Sox & Martin Super Stock Barracuda",
        "real_car": "",
        "photo_loose": "",
        "photo_carded": ""
    },
    "country": "",
    "notes": "Goodyear RR5SP",
    "images": {
        "0": "https://static.wikia.nocookie.net/hotwheels/images/6/68/Cuda.jpg/revision/latest?cb=20100628040921"
    }
}