{
    "release_id": "0-flying-customs-series-2006-orange-l7407",
    "toy_number": "L7407",
    "casting_id": "flying-customs-series-2006",
    "year": 0,
    "series_id": "unknown",
    "series_index": null,
    "specs": {
        "color": "Orange",
        "tampo": "",
        "base_color": "",
        "base_type": "",
        "window_color": "",
        "interior_color": "",
        "wheel_type": {
            "0": ""
        },
        "casting_name": "Camaro Z-28",
        "notes_variations": "",
        "photo_loose": "",
        "photo_carded": ""
    },
    "country": "Malaysia",
    "notes": "",
    "images": {
        "0": "https://static.wikia.nocookie.net/hotwheels/images/b/b7/Camaro_Z-28_-_07_Flying_Customs.jpg/revision/latest?cb=20081203025935"
    }
}