{
    "release_id": "0-premium-collector-set-rr8sp-volkswagen-transporter-t1-pickup",
    "toy_number": "Volkswagen Transporter T1 Pickup",
    "casting_id": "premium-collector-set",
    "year": 0,
    "series_id": "unknown",
    "series_index": null,
    "specs": {
        "color": "RR8SP",
        "tampo": "",
        "base_color": "",
        "base_type": "",
        "window_color": "",
        "interior_color": "",
        "wheel_type": {
            "0": "Base code(s): T03, T04, T06"
        },
        "casting_name": "Red",
        "photo_loose": "",
        "photo_boxed": ""
    },
    "country": "",
    "notes": "",
    "images": {
        "0": "https://static.wikia.nocookie.net/hotwheels/images/9/97/PorschePickup.jpg/revision/latest?cb=20240316100244"
    }
}