{
    "release_id": "0-racing-rigs-green-octainium",
    "toy_number": "Octainium",
    "casting_id": "racing-rigs",
    "year": 0,
    "series_id": "unknown",
    "series_index": null,
    "specs": {
        "color": "Green",
        "tampo": "",
        "base_color": "",
        "base_type": "",
        "window_color": "",
        "interior_color": "",
        "wheel_type": {
            "0": ""
        },
        "vehicles": "Chrome & green",
        "notes_variations": "",
        "photo_loose": "",
        "photo_carded": ""
    },
    "country": "China",
    "notes": "",
    "images": {
        "0": "https://static.wikia.nocookie.net/hotwheels/images/6/64/OCTANIUM_UFO_SQUAD.jpg/revision/latest?cb=20230611215803"
    }
}