{
    "release_id": "0-since-68-series-orange-m1555",
    "toy_number": "M1555",
    "casting_id": "since-68-series",
    "year": 0,
    "series_id": "unknown",
    "series_index": null,
    "specs": {
        "color": "Orange",
        "tampo": "",
        "base_color": "",
        "base_type": "",
        "window_color": "",
        "interior_color": "",
        "wheel_type": {
            "0": ""
        },
        "series": "40/40",
        "model_name": "Go Kart",
        "photo_loose": "​",
        "photo_carded": "​"
    },
    "country": "",
    "notes": "",
    "images": {
        "0": "https://static.wikia.nocookie.net/hotwheels/images/4/4e/DSCN3389-1-.jpg/revision/latest?cb=20120722210812"
    }
}