{
    "release_id": "jjj60-renault-espace-f1-2026",
    "toy_number": "JJJ60",
    "casting_id": "renault-espace-f1",
    "year": 2026,
    "series_id": "hw-starting-grid",
    "series_index": 6,
    "specs": {
        "color": "Blue",
        "tampo": "Detailed headlights and side vents, Hot Wheels logo, \"Team HW\", \"1\", \" ATN \", white and black livery and Michelin man on sides",
        "base_color": "",
        "base_type": "Plastic",
        "window_color": "Smoke tint",
        "interior_color": "Blue",
        "wheel_type": {
            "0": "Chrome Orange L4"
        }
    },
    "country": "Malaysia",
    "notes": "Base code(s): U44N",
    "images": {
        "0": "https://static.wikia.nocookie.net/hotwheels/images/4/4d/RacingEspace.jpg/revision/latest?cb=20251216111129"
    }
}