[
    {
        "metadata": {
            "name": "1970 Pontiac Firebird",
            "Debut series": "HW Dream Garage",
            "image": "'70PontiacFirebird.jpg",
            "image_url": "https://static.wikia.nocookie.net/hotwheels/images/5/5b/%2770PontiacFirebird.jpg/revision/latest/scale-to-width-down/268?cb=20211012082657"
        },
        "description": {
            "en-us": "1970 Pontiac Firebird Debut series HW Dream Garage Produced 2022 – Present Designer Riley Stair , Brendon Vetuskey and Manson Cheung Number HCT05",
            "pt-br": ""
        },
        "releases": [
            {
                "Col #": "001/250",
                "Year": "2022",
                "Series": "HW Dream Garage 1/5",
                "Color": "White",
                "Tampo": "Front light covers, sponsor decals, detailed taillights",
                "base_color": "Black",
                "base_type": "Plastic",
                "Window Color": "Smoke tint",
                "Interior Color": "Dark chrome",
                "Wheel Type": "5SP / Front light covers, sponsor decals, detailed taillights, Black Slot decal on Side",
                "Toy #": "HCT05",
                "Country": "Malaysia",
                "Notes / Variations": "New Model Base code(s): P38, P41",
                "Photo": "https://static.wikia.nocookie.net/hotwheels/images/5/5b/%2770PontiacFirebird.jpg/revision/latest/scale-to-width-down/75?cb=20211012082657"
            },
            {
                "Col #": "001/250",
                "Year": "2022",
                "Series": "HW Dream Garage 1/5",
                "Color": "Red",
                "Tampo": "Front light covers, sponsor decals, detailed taillights",
                "base_color": "Black",
                "base_type": "Plastic",
                "Window Color": "Smoke tint",
                "Interior Color": "Chrome",
                "Wheel Type": "5SP / Front light covers, sponsor decals, detailed taillights, Black Slot decal on Side",
                "Toy #": "HCX22",
                "Country": "Malaysia",
                "Notes / Variations": "New Model Base code(s): R10, R12, R15",
                "Photo": "https://static.wikia.nocookie.net/hotwheels/images/0/0c/PontiacFirebird_Front.png/revision/latest/scale-to-width-down/75?cb=20221004155332"
            },
            {
                "Col #": "018/250",
                "Year": "2023",
                "Series": "HW Modified 2/5",
                "Color": "Metallic Light Blue",
                "Tampo": "Blue, Light Blue, and White lines, \"70\" on roof and sides, \"GOODYEAR\" and HW logo on sides",
                "base_color": "Black",
                "base_type": "Plastic",
                "Window Color": "Smoke tint",
                "Interior Color": "Chrome",
                "Wheel Type": "5SP",
                "Toy #": "HKH83",
                "Country": "Malaysia",
                "Notes / Variations": "Base code(s): R33",
                "Photo": "https://static.wikia.nocookie.net/hotwheels/images/c/c8/HKH83.jpg/revision/latest/scale-to-width-down/75?cb=20221105115100"
            },
            {
                "Col #": "018/250",
                "Year": "2023",
                "Series": "HW Modified 2/5",
                "Color": "Orange",
                "Tampo": "Black and Yellow lines, \"70\" on roof and sides, \"GOODYEAR\" and HW logo on sides",
                "base_color": "Gray",
                "base_type": "Plastic",
                "Window Color": "Smoke tint",
                "Interior Color": "Chrome",
                "Wheel Type": "5SP",
                "Toy #": "HKK48",
                "Country": "Malaysia",
                "Notes / Variations": "Kroger Exclusive Base code(s):",
                "Photo": "https://static.wikia.nocookie.net/hotwheels/images/f/f9/1970_Pontiac_Firebird.jpg/revision/latest/scale-to-width-down/75?cb=20230706002102"
            },
            {
                "Col #": "018/250",
                "Year": "2023",
                "Series": "HW Modified 2/5",
                "Color": "Metalflake Violet",
                "Tampo": "Pink and white lines, \"70\" on roof and sides, \"GOODYEAR\" and HW logo on sides",
                "base_color": "Black",
                "base_type": "Plastic",
                "Window Color": "Smoke tint",
                "Interior Color": "Chrome",
                "Wheel Type": "Gray 5SP",
                "Toy #": "HKK49",
                "Country": "Malaysia",
                "Notes / Variations": "Base code(s): S15, S19, S21",
                "Photo": "https://static.wikia.nocookie.net/hotwheels/images/c/c5/HKK49.jpg/revision/latest/scale-to-width-down/75?cb=20230521104943"
            },
            {
                "Col #": "",
                "Year": "2024",
                "Series": "Hot Wheels Legends Tour Themed Multipack",
                "Color": "White",
                "Tampo": "Front light covers, sponsor decals, detailed taillights",
                "base_color": "Black",
                "base_type": "Plastic",
                "Window Color": "Smoke tint",
                "Interior Color": "Chrome",
                "Wheel Type": "Gold S5",
                "Toy #": "HRX55",
                "Country": "Thailand",
                "Notes / Variations": "Base code(s): S45",
                "Photo": "https://static.wikia.nocookie.net/hotwheels/images/2/28/20250403202148.jpg/revision/latest/scale-to-width-down/75?cb=20250404012200"
            }
        ]
    }
]