{
    "release_id": "ghd75-dodge-viper-rt-10-2020",
    "toy_number": "GHD75",
    "casting_id": "dodge-viper-rt-10",
    "year": 2020,
    "series_id": "hw-race-team",
    "series_index": 5,
    "specs": {
        "color": "",
        "tampo": "",
        "base_color": "",
        "base_type": "Plastic",
        "window_color": "Blue tint",
        "interior_color": "Gray",
        "wheel_type": {
            "0": "MC5"
        }
    },
    "country": "Malaysia",
    "notes": "Treasure Hunt Base code(s): N30, N31",
    "images": {
        "0": "https://static.wikia.nocookie.net/hotwheels/images/4/44/2020_Hot_Wheels_Dodge_Viper.png/revision/latest/scale-to-width-down/75?cb=20201018184823"
    }
}