{
    "release_id": "ghg45-92-bmw-m3-2020",
    "toy_number": "GHG45",
    "casting_id": "92-bmw-m3",
    "year": 2020,
    "series_id": "hw-rescue",
    "series_index": 4,
    "specs": {
        "color": "ZAMAC",
        "tampo": "Blue Striping with 'POLIZEI' on sides & hood. Hot Wheels logo on sides. 'W8303' on sides of rear bumper",
        "base_color": "",
        "base_type": "Plastic",
        "window_color": "Light blue tint",
        "interior_color": "Black",
        "wheel_type": {
            "0": "WPR5"
        }
    },
    "country": "Malaysia",
    "notes": "Walmart Exclusive Base code(s): N11, N24",
    "images": {
        "0": "https://static.wikia.nocookie.net/hotwheels/images/5/5a/%2792_BMW_M3_Zamac.jpg/revision/latest/scale-to-width-down/75?cb=20210317004907"
    }
}