{
    "release_id": "1973-mercedes-benz-c-111-enamel-red-6978",
    "toy_number": "6978",
    "casting_id": "mercedes-benz-c-111",
    "year": 1973,
    "series_id": "mainline",
    "series_index": null,
    "specs": {
        "color": "Enamel Red",
        "tampo": "",
        "base_color": "Unpainted",
        "base_type": "Metal",
        "window_color": "Tinted (Blue)",
        "interior_color": "White or Brown",
        "wheel_type": {
            "0": "RL"
        }
    },
    "country": "Hong Kong",
    "notes": "Capped Rear Wheels",
    "images": {
        "0": "https://static.wikia.nocookie.net/hotwheels/images/5/58/1973_Mercedes-Benz_C-111_enamel_Red_Capped_Rear_Wheels.jpg/revision/latest?cb=20211208100536"
    }
}