{
    "release_id": "2011-deora-spectraflame-blue-v0494",
    "toy_number": "V0494",
    "casting_id": "deora",
    "year": 2011,
    "series_id": "hwccom",
    "series_index": null,
    "specs": {
        "color": "Spectraflame Blue",
        "tampo": "\"SKY SHOW\" on black and white checkered tampo on sides",
        "base_color": "Chrome",
        "base_type": "Metal",
        "window_color": "Clear",
        "interior_color": "White",
        "wheel_type": {
            "0": "NCRL"
        },
        "col": "199",
        "notes_variations": "Named Sky Show Dodge Deora Concept 2,500 produced Production code(s): 0452 WA"
    },
    "country": "China",
    "notes": "",
    "images": {
        "0": "https://static.wikia.nocookie.net/hotwheels/images/7/7b/Sky_Show_Deora_2011.jpg/revision/latest?cb=20120302202312"
    }
}