{
    "release_id": "11897-olds-442-w-30-1994",
    "toy_number": "11897",
    "casting_id": "olds-442-w-30",
    "year": 1994,
    "series_id": "greater-seattle-toy-show",
    "series_index": null,
    "specs": {
        "color": "Black",
        "tampo": "White stripes on hood, Greater Seattle Toy Show logo on roof",
        "base_color": "",
        "base_type": "Plastic",
        "window_color": "Clear",
        "interior_color": "White",
        "wheel_type": {
            "0": "Gray DDRR"
        }
    },
    "country": "Malaysia",
    "notes": "7,000 produced",
    "images": {
        "0": "https://static.wikia.nocookie.net/hotwheels/images/0/0b/Greater_Seattle_Toy_Show_1970_Olds_442_Black_11897.jpg/revision/latest/scale-to-width-down/75?cb=20220725223454"
    }
}