{
    "release_id": "dht82-porsche-993-gt2-2016",
    "toy_number": "DHT82",
    "casting_id": "porsche-993-gt2",
    "year": 2016,
    "series_id": "hw-showroom",
    "series_index": 4,
    "specs": {
        "color": "Spectraflame Dark Blue",
        "tampo": "Black hood, Orange stripe on top, 'Porsche' on spoiler, 'TH' on roof",
        "base_color": "",
        "base_type": "Plastic",
        "window_color": "Clear",
        "interior_color": "White",
        "wheel_type": {
            "0": "Orange RREx",
            "1": "Super Treasure Hunt Full Roll Cage variation (RARE) Base code(s): H42",
            "2": "H43"
        }
    },
    "country": "Malaysia",
    "notes": "Super Treasure Hunt Half Roll Cage variation Base code(s): H42, H43, H44",
    "images": {
        "0": "https://static.wikia.nocookie.net/hotwheels/images/9/98/Gt2superthunt2016.jpg/revision/latest/scale-to-width-down/75?cb=20171113100156"
    }
}