{
    "release_id": "dhx37-72-ford-gran-torino-sport-2016",
    "toy_number": "DHX37",
    "casting_id": "72-ford-gran-torino-sport",
    "year": 2016,
    "series_id": "muscle-mania",
    "series_index": 2,
    "specs": {
        "color": "Black",
        "tampo": "Black & Grey stripes on sides & hood, Grey HW logo on trunk",
        "base_color": "",
        "base_type": "Plastic",
        "window_color": "Clear",
        "interior_color": "Chrome",
        "wheel_type": {
            "0": "Chrome Red & Black MC5"
        }
    },
    "country": "Malaysia",
    "notes": "Base code(s): J26, J27, J28, J30",
    "images": {
        "0": "https://static.wikia.nocookie.net/hotwheels/images/a/a9/72_FGT_DHX37.jpg/revision/latest/scale-to-width-down/75?cb=20170910075117"
    }
}